{
  "Db.Common.UserPreference.EntityPlural": "Kullanıcı Tercihleri",
  "Db.Common.UserPreference.EntitySingular": "Kullanıcı Tercihi",
  "Db.Common.UserPreference.Name": "İsim",
  "Db.Common.UserPreference.PreferenceType": "Tercih Tipi",
  "Db.Common.UserPreference.UserId": "Kullanıcı ID",
  "Db.Common.UserPreference.UserPreferenceId": "ID",
  "Db.Common.UserPreference.Value": "Değer",
  "Forms.Membership.ChangePassword.ConfirmPassword": "Şifreyi Onayla",
  "Forms.Membership.ChangePassword.ElevatedActions": null,
  "Forms.Membership.ChangePassword.FormTitle": "Şifre Değiştir",
  "Forms.Membership.ChangePassword.NewPassword": "Yeni Şifre",
  "Forms.Membership.ChangePassword.OldPassword": "Mevcut Şifre",
  "Forms.Membership.ChangePassword.PasswordNotSet": null,
  "Forms.Membership.ChangePassword.SetPassword": null,
  "Forms.Membership.ChangePassword.SetPasswordButton": null,
  "Forms.Membership.ChangePassword.SetPasswordInfo": null,
  "Forms.Membership.ChangePassword.SetPasswordSuccess": null,
  "Forms.Membership.ChangePassword.SubmitButton": "Şifre Değiştir",
  "Forms.Membership.ChangePassword.Success": "Şifreniz değiştirildi.",
  "Forms.Membership.ForgotPassword.Email": "E-posta Adresi",
  "Forms.Membership.ForgotPassword.Email_Placeholder": "e-posta",
  "Forms.Membership.ForgotPassword.FormInfo": "Lütfen kayıt olurken kullandığınız e-postayı girin.",
  "Forms.Membership.ForgotPassword.FormTitle": "Şifremi Unuttum",
  "Forms.Membership.ForgotPassword.SubmitButton": "Şifremi Sıfırla",
  "Forms.Membership.ForgotPassword.SuccessMessage": "Bu kullanıcı varsa, size şifre sıfırlama talimatları içeren bir e-posta gönderdik.",
  "Forms.Membership.ResetPassword.ConfirmPassword": "Şifreyi Onayla",
  "Forms.Membership.ResetPassword.ConfirmPassword_Placeholder": "şifreyi onayla",
  "Forms.Membership.ResetPassword.EmailSubject": "Şifrenizi Sıfırlayın",
  "Forms.Membership.ResetPassword.FormTitle": "Şifre Sıfırla",
  "Forms.Membership.ResetPassword.NewPassword": "Yeni Şifre",
  "Forms.Membership.ResetPassword.NewPassword_Placeholder": "şifre",
  "Forms.Membership.ResetPassword.SubmitButton": "Şifremi Sıfırla",
  "Forms.Membership.ResetPassword.Success": "Parolanız değiştirildi. Lütfen yeni şifrenizle giriş yapın.",
  "Site.BasicProgressDialog.CancelTitle": "İşlem iptal edildi. Devam eden işlemin tamamlanması bekleniyor...",
  "Site.BasicProgressDialog.PleaseWait": "Lütfen bekleyiniz...",
  "Site.BulkServiceAction.AllHadErrorsFormat": "İşlem yapılmak istenen {0} kayıtta hata alındı!",
  "Site.BulkServiceAction.AllSuccessFormat": "{0} kayıt üzerinde başarıyla işlem yapıldı.",
  "Site.BulkServiceAction.ConfirmationFormat": "Seçilen {0} kayıtta bu işlemi gerçekleştirmek istiyor musunuz?",
  "Site.BulkServiceAction.ErrorCount": "{0} hatalı",
  "Site.BulkServiceAction.NothingToProcess": "Lütfen işlem yapılacak kayıtları seçiniz!",
  "Site.BulkServiceAction.SomeHadErrorsFormat": "{0} kayıt üzerinde başarıyla işlem yapıldı. {1} kayıtta hata alındı!",
  "Site.BulkServiceAction.SuccessCount": "{0} başarılı",
  "Site.Dialogs.PendingChangesConfirmation": "Bekleyen değişiklikleriniz var. Kaydetmek ister misiniz?",
  "Site.Translation.Assembly": "Assembly",
  "Site.Translation.CopyFailMessage": "Panoya kopyalama başarısız oldu! HTTPS veya gerekli izinlere sahip olunmaması nedeniyle olabilir.",
  "Site.Translation.CopySourceTranslations": "Kaynak metinleri JSON formatında panoya kopyala",
  "Site.Translation.CopySuccessMessage": "Metinler JSON formatında panoya kopyalandı.",
  "Site.Translation.CopyTargetTranslations": "Hedef metinleri JSON formatında panoya kopyala",
  "Site.Translation.CustomText": "Hedef Dilde Kullanıcı Çevirisi",
  "Site.Translation.EntityPlural": "Çeviriler",
  "Site.Translation.HasTranslation": "Çevirisi Var",
  "Site.Translation.Key": "Yerel Metin Anahtarı",
  "Site.Translation.OverrideConfirmation": "Tıklanan metin kullanıcı çevirisinin üzerine yazılsın mı?",
  "Site.Translation.SaveChangesButton": "Değişiklikleri Kaydet",
  "Site.Translation.SaveSuccessMessage": "Kullanıcının hedef dildeki çevirileri {0} olarak kaydedildi",
  "Site.Translation.SourceLanguage": "Kaynak Dil",
  "Site.Translation.SourceText": "Kaynak Dilde Etkin Çeviri",
  "Site.Translation.TargetLanguage": "Hedef Dil",
  "Site.Translation.TargetText": "Hedef Dilde Etkin Çeviri",
  "Site.Translation.UserTranslated": "Kullanıcı Çevirisi Var",
  "Validation.InvalidResetToken": "Parolanızı sıfırlamak için kullandığınız belirteciniz geçersiz veya süresi dolmuş!",
  "Validation.MinRequiredPasswordLength": "Girilen parolada yeterli uzunlukta değil (en az {0})!",
  "Validation.PasswordConfirmMismatch": "Girilen parolalar eşleşmiyor!"
}